setup.cfg
setup.py
bin/recone
recone/__init__.py
recone/cli.py
recone/messages.py
recone/utils.py
recone/version.py
recone.egg-info/PKG-INFO
recone.egg-info/SOURCES.txt
recone.egg-info/dependency_links.txt
recone.egg-info/requires.txt
recone.egg-info/top_level.txt
recone/nodes/__init__.py
recone/nodes/base.py
recone/nodes/broker.py
recone/nodes/client.py
recone/nodes/client_master.py
recone/nodes/client_servant.py