Metadata-Version: 1.1
Name: recone
Version: 0.0.2
Summary: Framework to remote control a network of clients.
Home-page: https://github.com/tbleiker/recone
Author: Tobias Bleiker and Dumeni Manatschal
Author-email: UNKNOWN
License: UNKNOWN
Platform: UNKNOWN
Classifier: License :: OSI Approved :: GNU Affero General Public License v3
Classifier: Programming Language :: Python :: 3.5
Classifier: Programming Language :: Python :: 3 :: Only
Classifier: Topic :: Communications
